{
  "agence": [
    {
      "id": "277",
      "ville": "791",
      "type": "2",
      "nom": "Bouskoura",
      "horaire1": "DU LUNDI AU VENDREDI",
      "horaire2": "08:15 - 15:45",
      "horaire3": " ",
      "horaire4": " ",
      "horaire5": " ",
      "horaire6": " ",
      "adresse": "9, Lot Lagarge, Jemaa Ouled Abbou - Bouskoura",
      "telephone1": "05 22 59 08 34",
      "telephone2": "00212522590834",
      "fax": "05 22 59 08 36",
      "latitude": "33.45137390",
      "longitude": "-7.64836250",
      "distance": "1014.988758198744"
    },
    {
      "id": "1266",
      "ville": "795",
      "type": "1",
      "nom": "Oulad Salah",
      "horaire1": "DU LUNDI AU VENDREDI",
      "horaire2": "08:15 - 15:45",
      "horaire3": " ",
      "horaire4": " ",
      "horaire5": " ",
      "horaire6": " ",
      "adresse": "Quartier Industriel Oulad Saleh",
      "telephone1": "05 29 02 87 56",
      "telephone2": "00212529028756",
      "fax": "05 29 02 87 55",
      "latitude": "33.43212440",
      "longitude": "-7.63942890",
      "distance": "3123.6753168071305"
    },
    {
      "id": "1531",
      "ville": "791",
      "type": "1",
      "nom": "Bouskoura Ville Verte",
      "horaire1": "DU LUNDI AU VENDREDI",
      "horaire2": "08:15 - 15:45",
      "horaire3": " ",
      "horaire4": " ",
      "horaire5": " ",
      "horaire6": " ",
      "adresse": "N 11, One Hill, Promenade du Golf, Bouskoura",
      "telephone1": "0529081516",
      "telephone2": "0529081516",
      "fax": "0529081513",
      "latitude": "33.49761110",
      "longitude": "-7.60719444",
      "distance": "5439.477170886245"
    },
    {
      "id": "241",
      "ville": "780",
      "type": "1",
      "nom": "Casa Sidi Maarouf Expansion",
      "horaire1": "DU LUNDI AU VENDREDI",
      "horaire2": "08:15 - 15:45",
      "horaire3": " ",
      "horaire4": " ",
      "horaire5": " ",
      "horaire6": " ",
      "adresse": "Lot N° 154, Route CT 1100, Lot Melk Dandoun - Casablanca",
      "telephone1": "05 22 58 46 34",
      "telephone2": "00212522584634",
      "fax": "05 22 58 46 43",
      "latitude": "33.51456250",
      "longitude": "-7.64886280",
      "distance": "6101.78201756948"
    },
    {
      "id": "110",
      "ville": "780",
      "type": "2",
      "nom": "Casa Sidi Maarouf",
      "horaire1": "DU LUNDI AU VENDREDI",
      "horaire2": "08:15 - 15:45",
      "horaire3": " ",
      "horaire4": " ",
      "horaire5": " ",
      "horaire6": " ",
      "adresse": "Lot Najah, N° 18, Sidi Maârouf - Casablanca",
      "telephone1": "05 22 97 36 40",
      "telephone2": "00212522973640",
      "fax": "05 22 33 50 39",
      "latitude": "33.51566040",
      "longitude": "-7.65449890",
      "distance": "6280.206684107789"
    },
    {
      "id": "1532",
      "ville": "780",
      "type": "1",
      "nom": "Casa Quartier Florida",
      "horaire1": "DU LUNDI AU VENDREDI",
      "horaire2": "08:15 - 15:45",
      "horaire3": " ",
      "horaire4": " ",
      "horaire5": " ",
      "horaire6": " ",
      "adresse": "Florida Center Park 2, Lot N 8, Sidi Maarouf, Casablanca",
      "telephone1": "0529081798",
      "telephone2": "+212529081798",
      "fax": "0529081795",
      "latitude": "33.52036940",
      "longitude": "-7.63525555",
      "distance": "6787.63436167655"
    },
    {
      "id": "1029",
      "ville": "780",
      "type": "1",
      "nom": "Casa Sidi Maarouf Al Mawlid",
      "horaire1": "DU LUNDI AU VENDREDI",
      "horaire2": "08:15 - 15:45",
      "horaire3": " ",
      "horaire4": " ",
      "horaire5": " ",
      "horaire6": " ",
      "adresse": "Résidence Al Mawlid , Immeuble A2 , Route Sidi Maarouf",
      "telephone1": "05 22 97 53 72",
      "telephone2": "00212522975372",
      "fax": "05 22 97 53 65",
      "latitude": "33.52584700",
      "longitude": "-7.65076700",
      "distance": "7367.618202668251"
    },
    {
      "id": "695",
      "ville": "780",
      "type": "1",
      "nom": "Casa Ennassim",
      "horaire1": "DU LUNDI AU VENDREDI",
      "horaire2": "08:15 - 15:45",
      "horaire3": " ",
      "horaire4": " ",
      "horaire5": " ",
      "horaire6": " ",
      "adresse": "Lot Ennassim, Quartier Lissasfa - Casablanca",
      "telephone1": "05 22 93 66 75",
      "telephone2": "00212522936675",
      "fax": "05 22 93 54 31",
      "latitude": "33.52539650",
      "longitude": "-7.66046640",
      "distance": "7444.530104143378"
    },
    {
      "id": "906",
      "ville": "780",
      "type": "1",
      "nom": "Casa La Colline Expansion",
      "horaire1": "DU LUNDI AU VENDREDI",
      "horaire2": "08:15 - 15:45",
      "horaire3": " ",
      "horaire4": " ",
      "horaire5": " ",
      "horaire6": " ",
      "adresse": "Near Shoore Park, Shore 9, 1100, Bd. El Qods, Sidi Maârouf - Casablanca",
      "telephone1": "05 29 04 48 22",
      "telephone2": "00212529044822",
      "fax": "05 29 01 43 57",
      "latitude": "33.52736140",
      "longitude": "-7.64107070",
      "distance": "7518.941180513049"
    },
    {
      "id": "670",
      "ville": "780",
      "type": "1",
      "nom": "Casa Lissasfa",
      "horaire1": "DU LUNDI AU VENDREDI",
      "horaire2": "08:15 - 15:45",
      "horaire3": " ",
      "horaire4": " ",
      "horaire5": " ",
      "horaire6": " ",
      "adresse": "29, Bd. Atlas, Quartier Lissasfa - Casablanca",
      "telephone1": "05 22 65 45 75",
      "telephone2": "00212522654575",
      "fax": "05 22 65 28 50",
      "latitude": "33.53585980",
      "longitude": "-7.66244090",
      "distance": "8622.562783057814"
    }
  ]
}